{
	"format_version": "1.12.0",
	"minecraft:geometry": [
		{
			"description": {
				"identifier": "mothercreeper.geo",
				"texture_width": 64,
				"texture_height": 32,
				"visible_bounds_width": 3,
				"visible_bounds_height": 3.5,
				"visible_bounds_offset": [0, 1.25, 0]
			},
			"bones": [
				{
					"name": "root",
					"pivot": [0, 0, -4]
				},
				{
					"name": "Neck",
					"parent": "root",
					"pivot": [0, 0, -6],
					"cubes": [
						{"origin": [-2.5, 6.025, -6], "size": [5.25, 1.5, 4], "uv": [38, 0]},
						{"origin": [-2.5, 4.5, -6], "size": [5.25, 1.5, 4], "uv": [24, 28]}
					]
				},
				{
					"name": "bone",
					"parent": "root",
					"pivot": [0, 0, -4],
					"cubes": [
						{"origin": [-2.5, 4.5, -2.025], "size": [5.25, 3.525, 8.55], "uv": [13, 13]},
						{"origin": [-2.5, 7.20453, -7.38998], "size": [5.25, 1.5, 4], "pivot": [0.125, 1.70453, -5.38998], "rotation": [-14, 0, 0], "uv": [46, 0]},
						{"origin": [-2.5, 7.64369, -5.58329], "size": [5.25, 1.5, 4], "pivot": [0.125, 8.39369, -3.58329], "rotation": [-36.5, 0, 0], "uv": [10, 20]},
						{"origin": [-2.5, 9.14369, -5.58329], "size": [5.25, 1.5, 4], "pivot": [0.125, 8.39369, -3.58329], "rotation": [-36.5, 0, 0], "uv": [42, 2]},
						{"origin": [-2.5, 10.64369, -5.58329], "size": [5.25, 1.5, 4], "pivot": [0.125, 8.39369, -3.58329], "rotation": [-36.5, 0, 0], "uv": [21, 24]},
						{"origin": [-2.5, 12.09369, -5.58329], "size": [5.25, 2.8, 4], "pivot": [0.125, 8.39369, -3.58329], "rotation": [-36.5, 0, 0], "uv": [45, 4]},
						{"origin": [-2.5, 13.16616, -2.22694], "size": [5.25, 1.35, 4], "pivot": [0.125, 12.54116, -0.22694], "rotation": [-20.25, 0, 0], "uv": [18, 22]},
						{"origin": [-2.5, 13.70948, -1.64945], "size": [5.25, 1.4, 4], "pivot": [0.125, 11.68448, 0.35055], "rotation": [0.5, 0, 0], "uv": [19, 24]},
						{"origin": [-2.5, 14.72944, -1.16701], "size": [5.25, 1.4, 4], "pivot": [0.125, 12.67944, 0.83299], "rotation": [13, 0, 0], "uv": [14, 21]},
						{"origin": [-2.5, 15.46091, -2.08745], "size": [5.25, 1.4, 4], "pivot": [0.125, 16.16091, -0.08745], "rotation": [28.25, 0, 0], "uv": [15, 10]},
						{"origin": [-2.5, 16.0635, -2.54568], "size": [5.25, 1.4, 4], "pivot": [0.125, 16.7635, -0.54568], "rotation": [46.25, 0, 0], "uv": [13, 21]},
						{"origin": [-2.5, 17.3135, -2.54568], "size": [5.25, 1.65, 4], "pivot": [0.125, 16.7635, -0.54568], "rotation": [46.25, 0, 0], "uv": [22, 22]},
						{"origin": [-3.75, 16.75, -8.25], "size": [8, 7.75, 7.5], "uv": [1, 2]}
					]
				},
				{
					"name": "bone6",
					"parent": "root",
					"pivot": [-6.40694, 5.05002, -4.225],
					"cubes": [
						{"origin": [-3.875, 5.25, -5.325], "size": [2.15, 2.175, 2.2], "pivot": [-4.15, 6.3375, -3.15], "rotation": [0, 0, 21.75], "uv": [52, 7], "mirror": true},
						{"origin": [-6.05, 5.5, -5.075], "size": [2.15, 1.675, 1.7], "pivot": [-4.15, 6.3375, -3.15], "rotation": [0, 0, 21.75], "uv": [58, 24], "mirror": true},
						{"origin": [-11.20833, 5.92408, -5.075], "size": [6.2, 1.325, 1.7], "pivot": [-6.28333, 6.51158, -4.225], "rotation": [0, 0, -32.75], "uv": [6, 21], "mirror": true},
						{"origin": [-13.63342, 0.70132, -5.075], "size": [4.65, 1.5, 1.7], "pivot": [-10.95842, 2.43882, -4.225], "rotation": [0, 0, -92.5], "uv": [2, 24], "mirror": true}
					]
				},
				{
					"name": "bone5",
					"parent": "root",
					"pivot": [6.40694, 5.05002, 4.675],
					"cubes": [
						{"origin": [1.725, 5.25, 3.575], "size": [2.15, 2.175, 2.2], "pivot": [4.15, 6.3375, 3.6], "rotation": [0, 0, -21.75], "uv": [41, 0]},
						{"origin": [3.9, 5.5, 3.825], "size": [2.15, 1.675, 1.7], "pivot": [4.15, 6.3375, 3.6], "rotation": [0, 0, -21.75], "uv": [46, 2]},
						{"origin": [5.00833, 5.92408, 3.825], "size": [6.2, 1.325, 1.7], "pivot": [6.28333, 6.51158, 4.675], "rotation": [0, 0, 32.75], "uv": [23, 30]},
						{"origin": [8.98342, 0.70132, 3.825], "size": [4.65, 1.5, 1.7], "pivot": [10.95842, 2.43882, 4.675], "rotation": [0, 0, 92.5], "uv": [2, 24]}
					]
				},
				{
					"name": "bone7",
					"parent": "root",
					"pivot": [0.75, 0, -3.75],
					"cubes": [
						{"origin": [-3.875, 5.25, -0.675], "size": [2.15, 2.175, 2.2], "pivot": [-4.15, 6.3375, -0.65], "rotation": [0, 0, 21.75], "uv": [49, 3], "mirror": true},
						{"origin": [-6.05, 5.5, -0.425], "size": [2.15, 1.675, 1.7], "pivot": [-4.15, 6.3375, -0.65], "rotation": [0, 0, 21.75], "uv": [20, 27], "mirror": true},
						{"origin": [-11.20833, 5.92408, -0.425], "size": [6.2, 1.325, 1.7], "pivot": [-6.28333, 6.51158, 0.425], "rotation": [0, 0, -32.75], "uv": [40, 0], "mirror": true},
						{"origin": [-13.63342, 0.70132, -0.425], "size": [4.65, 1.5, 1.7], "pivot": [-10.95842, 2.43882, 0.425], "rotation": [0, 0, -92.5], "uv": [1, 24], "mirror": true}
					]
				},
				{
					"name": "bone8",
					"parent": "root",
					"pivot": [0.75, 0, -3.75],
					"cubes": [
						{"origin": [-3.875, 5.25, 3.575], "size": [2.15, 2.175, 2.2], "pivot": [-4.15, 6.3375, 3.6], "rotation": [0, 0, 21.75], "uv": [44, 1], "mirror": true},
						{"origin": [-6.05, 5.5, 3.825], "size": [2.15, 1.675, 1.7], "pivot": [-4.15, 6.3375, 3.6], "rotation": [0, 0, 21.75], "uv": [16, 28], "mirror": true},
						{"origin": [-11.20833, 5.92408, 3.825], "size": [6.2, 1.325, 1.7], "pivot": [-6.28333, 6.51158, 4.675], "rotation": [0, 0, -32.75], "uv": [50, 2], "mirror": true},
						{"origin": [-13.63342, 0.70132, 3.825], "size": [4.65, 1.5, 1.7], "pivot": [-10.95842, 2.43882, 4.675], "rotation": [0, 0, -92.5], "uv": [1, 24], "mirror": true}
					]
				},
				{
					"name": "bone2",
					"parent": "root",
					"pivot": [6.40694, 5.05002, 0.425],
					"cubes": [
						{"origin": [1.725, 5.25, -0.675], "size": [2.15, 2.175, 2.2], "pivot": [4.15, 6.3375, -0.65], "rotation": [0, 0, -21.75], "uv": [40, 0]},
						{"origin": [3.9, 5.5, -0.425], "size": [2.15, 1.675, 1.7], "pivot": [4.15, 6.3375, -0.65], "rotation": [0, 0, -21.75], "uv": [44, 0]},
						{"origin": [5.00833, 5.92408, -0.425], "size": [6.2, 1.325, 1.7], "pivot": [6.28333, 6.51158, 0.425], "rotation": [0, 0, 32.75], "uv": [16, 30]},
						{"origin": [8.98342, 0.70132, -0.425], "size": [4.65, 1.5, 1.7], "pivot": [10.95842, 2.43882, 0.425], "rotation": [0, 0, 92.5], "uv": [0, 24]}
					]
				},
				{
					"name": "bone3",
					"parent": "root",
					"pivot": [-0.5, 0, -3.5],
					"cubes": [
						{"origin": [-4.7, 4.95, -3.35], "size": [2.5, 1.9, 2.2], "pivot": [-1.1, 0, -3.5], "rotation": [-163.69835, 41.3385, -157.31796], "uv": [32, 8]},
						{"origin": [-2.6, 6.65, -2.95], "size": [4.7, 1.2, 1.2], "pivot": [-1.1, 0, -3.5], "rotation": [-136.30425, 7.94972, -98.80615], "uv": [30, 2]},
						{"origin": [-6.4, 5.35, -3.05], "size": [2.8, 1.2, 1.5], "pivot": [-1.1, 0, -3.5], "rotation": [-163.69835, 41.3385, -157.31796], "uv": [12, 12]}
					]
				},
				{
					"name": "bone4",
					"parent": "root",
					"pivot": [-0.75, 0, -3.75],
					"cubes": [
						{"origin": [1.725, 5.25, -5.325], "size": [2.15, 2.175, 2.2], "pivot": [4.15, 6.3375, -3.15], "rotation": [0, 0, -21.75], "uv": [15, 20]},
						{"origin": [3.9, 5.5, -5.075], "size": [2.15, 1.675, 1.7], "pivot": [4.15, 6.3375, -3.15], "rotation": [0, 0, -21.75], "uv": [56, 27]},
						{"origin": [5.00833, 5.92408, -5.075], "size": [6.2, 1.325, 1.7], "pivot": [6.28333, 6.51158, -4.225], "rotation": [0, 0, 32.75], "uv": [50, 1]},
						{"origin": [8.98342, 0.70132, -5.075], "size": [4.65, 1.5, 1.7], "pivot": [10.95842, 2.43882, -4.225], "rotation": [0, 0, 92.5], "uv": [1, 23]}
					]
				}
			]
		}
	]
}